mcp_serverman/__init__.py
mcp_serverman/cli.py
mcp_serverman/client.py
mcp_serverman/config.py
mcp_serverman/data/servers/mcp_tool_server.py
mcp_serverman-0.2.2.dist-info/LICENSE
mcp_serverman-0.2.2.dist-info/METADATA
mcp_serverman-0.2.2.dist-info/WHEEL
mcp_serverman-0.2.2.dist-info/entry_points.txt
mcp_serverman-0.2.2.dist-info/top_level.txt
mcp_serverman-0.2.2.dist-info/RECORD
