Metadata-Version: 2.2
Name: mcp-serverman
Version: 0.2.2
Summary: A tool to manage Claude MCP servers configuration
Home-page: https://github.com/benhaotang/mcp-serverman
Author: Benhao Tang
Author-email: benhaotang@outlook.com
Classifier: Programming Language :: Python :: 3
Classifier: License :: OSI Approved :: MIT License
Classifier: Operating System :: OS Independent
Requires-Python: >=3.6
License-File: LICENSE
Requires-Dist: click
Requires-Dist: rich
Requires-Dist: mcp>=1.3.0
Dynamic: author
Dynamic: author-email
Dynamic: classifier
Dynamic: description
Dynamic: description-content-type
Dynamic: home-page
Dynamic: requires-dist
Dynamic: requires-python
Dynamic: summary
